select_notifier/__init__.py
select_notifier/__version__.py
select_notifier/base.py
select_notifier/services/__init__.py
select_notifier/services/email.py
select_notifier/services/rocket.py
select_notifier/services/telegram.py
select_notifier-0.2.1.dist-info/METADATA
select_notifier-0.2.1.dist-info/WHEEL
select_notifier-0.2.1.dist-info/top_level.txt
select_notifier-0.2.1.dist-info/RECORD
