Metadata-Version: 2.4
Name: select-notifier
Version: 0.2.1
Summary: Lightweight notification package(email & Rocket.Chat, Telegram) for Select services
Author: Select Team
License: Proprietary
Project-URL: Homepage, https://repo.afe.ir/afeai/select-notifier
Requires-Python: >=3.9
Requires-Dist: httpx[http2]>=0.27.0
Requires-Dist: python-telegram-bot<22,>=21
Provides-Extra: test
Requires-Dist: pytest>=8; extra == "test"
Requires-Dist: pytest-cov>=5; extra == "test"
Provides-Extra: dev
Requires-Dist: black>=24.0; extra == "dev"
Requires-Dist: ruff>=0.6.0; extra == "dev"
Requires-Dist: mypy>=1.10; extra == "dev"
Requires-Dist: pre-commit>=3.7; extra == "dev"
